pdgen/__init__.py
pdgen/conftest.py
pdgen/converters/__init__.py
pdgen/converters/attribute_converter.py
pdgen/converters/attribute_converter_test.py
pdgen/converters/class_converter.py
pdgen/converters/class_converter_test.py
pdgen/converters/diagram_converter.py
pdgen/converters/diagram_converter_test.py
pdgen/converters/method_converter.py
pdgen/converters/method_converter_test.py
pdgen/decorators/__init__.py
pdgen/decorators/uml_decorators.py
pdgen/decorators/uml_decorators_test.py
pdgen/factories/__init__.py
pdgen/factories/attribute_factory/__init__.py
pdgen/factories/attribute_factory/attribute_factory.py
pdgen/factories/attribute_factory/attribute_factory_test.py
pdgen/factories/class_factory/__init__.py
pdgen/factories/class_factory/class_factory.py
pdgen/factories/class_factory/class_factory_test.py
pdgen/factories/diagram_factory/__init__.py
pdgen/factories/diagram_factory/diagram_factory.py
pdgen/factories/diagram_factory/diagram_factory_test.py
pdgen/factories/method_factory/__init__.py
pdgen/factories/method_factory/method_factory.py
pdgen/factories/method_factory/method_factory_test.py
pdgen/factories/type_hints/__init__.py
pdgen/factories/type_hints/type_hint_service.py
pdgen/factories/type_hints/type_hint_service_test.py
pdgen/factories/type_hints/type_information.py
pdgen/pytest.ini
pdgen/repositories/__init__.py
pdgen/repositories/class_repository.py
pdgen/repositories/class_repository_test.py
pdgen/setup/__init__.py
pdgen/setup/plant_uml_service_setup.py
pdgen/uml_generation/__init__.py
pdgen/uml_generation/plantuml_renderer.py
pdgen/uml_generation/plantuml_service.py
pdgen/uml_types/__init__.py
pdgen/uml_types/types.py
pdgen-0.3.2.dist-info/METADATA
pdgen-0.3.2.dist-info/WHEEL
pdgen-0.3.2.dist-info/RECORD
