Metadata-Version: 2.1
Name: pdgen
Version: 0.3.2
Summary: A package for generating UML Class diagrams from Python code
Home-page: https://github.com/Softoft/pdgen/
License: MIT
Author: Tobias Bück
Author-email: tab@softoft.de
Requires-Python: >=3.12
Classifier: Development Status :: 3 - Alpha
Classifier: Intended Audience :: Developers
Classifier: License :: OSI Approved :: MIT License
Classifier: Programming Language :: Python :: 3
Classifier: Programming Language :: Python :: 3.12
Classifier: Programming Language :: Python :: 3.13
Requires-Dist: plantuml
Requires-Dist: requests
Project-URL: Documentation, https://github.com/Softoft/pdgen/
Project-URL: Repository, https://github.com/Softoft/pdgen/
